{
  "critterInfos": [
    {
      "tagAttributeRates": [
        {
          "attributeId": 1,
          "rate": 0
        },
        {
          "attributeId": 2,
          "rate": 0
        },
        {
          "attributeId": 3,
          "rate": 0
        }
      ],
      "uid": 11003341,
      "defineId": 500006,
      "createTime": 1748915539,
      "efficiency": 460,
      "patience": 718,
      "lucky": 422,
      "efficiencyIncrRate": 9975,
      "patienceIncrRate": 8550,
      "luckyIncrRate": 9690,
      "specialSkin": false,
      "currentMood": 20000,
      "lock": false,
      "finishTrain": true,
      "trainInfo": null,
      "skillInfo": {
        "tags": [
          "xianjingdudu",
          "baseEfficiency_lv1",
          "basePatience_lv3",
          "baseIdea_lv1",
          "normal_patience_2"
        ]
      },
      "workInfo": null,
      "isHighQuality": false,
      "restInfo": {
        "buildingUid": 13101086,
        "restSlotId": 0
      },
      "trainHeroId": 3102,
      "totalFinishCount": 1,
      "name": ""
    },
    {
      "tagAttributeRates": [
        {
          "attributeId": 1,
          "rate": 0
        },
        {
          "attributeId": 2,
          "rate": 0
        },
        {
          "attributeId": 3,
          "rate": 0
        }
      ],
      "uid": 1210718,
      "defineId": 500009,
      "createTime": 1736545064,
      "efficiency": 400,
      "patience": 400,
      "lucky": 400,
      "efficiencyIncrRate": 8550,
      "patienceIncrRate": 9000,
      "luckyIncrRate": 9360,
      "specialSkin": false,
      "currentMood": 20000,
      "lock": false,
      "finishTrain": true,
      "trainInfo": null,
      "skillInfo": {
        "tags": [
          "jianfengzuanzi",
          "baseEfficiency_lv1",
          "basePatience_lv1",
          "baseIdea_lv1"
        ]
      },
      "workInfo": null,
      "isHighQuality": false,
      "restInfo": {
        "buildingUid": 13101086,
        "restSlotId": 1
      },
      "trainHeroId": 0,
      "totalFinishCount": 0,
      "name": ""
    },
    {
      "tagAttributeRates": [
        {
          "attributeId": 1,
          "rate": 0
        },
        {
          "attributeId": 2,
          "rate": 0
        },
        {
          "attributeId": 3,
          "rate": 0
        }
      ],
      "uid": 11003338,
      "defineId": 500007,
      "createTime": 1748915539,
      "efficiency": 424,
      "patience": 736,
      "lucky": 361,
      "efficiencyIncrRate": 9720,
      "patienceIncrRate": 8460,
      "luckyIncrRate": 8280,
      "specialSkin": false,
      "currentMood": 20000,
      "lock": false,
      "finishTrain": true,
      "trainInfo": null,
      "skillInfo": {
        "tags": [
          "fubingliequan",
          "baseEfficiency_lv1",
          "basePatience_lv3",
          "baseIdea_lv1",
          "normal_mix_4"
        ]
      },
      "workInfo": null,
      "isHighQuality": false,
      "restInfo": {
        "buildingUid": 13101086,
        "restSlotId": 5
      },
      "trainHeroId": 3023,
      "totalFinishCount": 2,
      "name": ""
    }
  ]
}
